pygenash/__init__.py
pygenash/analyse.py
pygenash/core.py
pygenash/inoutstream.py
pygenash/mainformstemplate.py
pygenash/template.py
pygenash/version.py
pygenash/templates/dead_end/description.xml
pygenash/templates/dead_end/display.xml
pygenash/templates/dead_end/redirect.js
pygenash/templates/dead_end/redirect.xml
pygenash/templates/muli_questions/compute.js.j2
pygenash/templates/muli_questions/description.xml.j2
pygenash/templates/muli_questions/display.xml.J2
pygenash/templates/muli_questions/redirect.js
pygenash/templates/muli_questions/redirect.xml
pygenash/templates/muli_questions/target_url.xml
pygenash/templates/one_choice/_error_display.xml
pygenash/templates/one_choice/compute.js
pygenash/templates/one_choice/description.xml
pygenash/templates/one_choice/display.xml
pygenash/templates/one_choice/redirect.js
pygenash/templates/one_choice/redirect.xml
pygenash/templates/one_choice/target_url.xml
pygenash/templates/voxusager/description.xml
pygenash/templates/voxusager/finished/display.xml
pygenash/templates/voxusager/finished/postprocess.xml
pygenash/templates/voxusager/finished/pushingbox.js
pygenash-1.0.11.dist-info/LICENSE.md
pygenash-1.0.11.dist-info/METADATA
pygenash-1.0.11.dist-info/WHEEL
pygenash-1.0.11.dist-info/entry_points.txt
pygenash-1.0.11.dist-info/top_level.txt
pygenash-1.0.11.dist-info/RECORD
