Metadata-Version: 2.1
Name: pygenash
Version: 1.0.11
Summary: UNKNOWN
Home-page: https://gitlab.com/guichet-entreprises.fr/tools/pygenash
Author: Florent Tournois
Author-email: florent.tournois@gmail.fr
License: MIT
Platform: UNKNOWN
Classifier: Programming Language :: Python
Classifier: Operating System :: OS Independent
Classifier: Programming Language :: Python :: 3
Classifier: Programming Language :: Python :: 3.6
Requires-Dist: jinja2
Requires-Dist: pyyaml
Requires-Dist: pydot
Requires-Dist: networkx
